d365fo_client/__init__.py
d365fo_client/auth.py
d365fo_client/cli.py
d365fo_client/client.py
d365fo_client/config.py
d365fo_client/credential_sources.py
d365fo_client/crud.py
d365fo_client/exceptions.py
d365fo_client/labels.py
d365fo_client/main.py
d365fo_client/metadata_api.py
d365fo_client/models.py
d365fo_client/odata_serializer.py
d365fo_client/output.py
d365fo_client/profile_manager.py
d365fo_client/profiles.py
d365fo_client/query.py
d365fo_client/session.py
d365fo_client/settings.py
d365fo_client/sync_models.py
d365fo_client/utils.py
d365fo_client/mcp/__init__.py
d365fo_client/mcp/client_manager.py
d365fo_client/mcp/fastmcp_main.py
d365fo_client/mcp/fastmcp_server.py
d365fo_client/mcp/fastmcp_utils.py
d365fo_client/mcp/main.py
d365fo_client/mcp/models.py
d365fo_client/mcp/server.py
d365fo_client/mcp/auth_server/__init__.py
d365fo_client/mcp/auth_server/dependencies.py
d365fo_client/mcp/auth_server/auth/__init__.py
d365fo_client/mcp/auth_server/auth/auth.py
d365fo_client/mcp/auth_server/auth/oauth_proxy.py
d365fo_client/mcp/auth_server/auth/redirect_validation.py
d365fo_client/mcp/auth_server/auth/providers/__init__.py
d365fo_client/mcp/auth_server/auth/providers/apikey.py
d365fo_client/mcp/auth_server/auth/providers/azure.py
d365fo_client/mcp/auth_server/auth/providers/bearer.py
d365fo_client/mcp/auth_server/auth/providers/jwt.py
d365fo_client/mcp/mixins/__init__.py
d365fo_client/mcp/mixins/base_tools_mixin.py
d365fo_client/mcp/mixins/connection_tools_mixin.py
d365fo_client/mcp/mixins/crud_tools_mixin.py
d365fo_client/mcp/mixins/database_tools_mixin.py
d365fo_client/mcp/mixins/label_tools_mixin.py
d365fo_client/mcp/mixins/metadata_tools_mixin.py
d365fo_client/mcp/mixins/performance_tools_mixin.py
d365fo_client/mcp/mixins/profile_tools_mixin.py
d365fo_client/mcp/mixins/sync_tools_mixin.py
d365fo_client/mcp/prompts/__init__.py
d365fo_client/mcp/prompts/action_execution.py
d365fo_client/mcp/prompts/sequence_analysis.py
d365fo_client/mcp/resources/__init__.py
d365fo_client-0.3.3.dist-info/licenses/LICENSE
d365fo_client-0.3.3.dist-info/METADATA
d365fo_client-0.3.3.dist-info/WHEEL
d365fo_client-0.3.3.dist-info/entry_points.txt
d365fo_client-0.3.3.dist-info/top_level.txt
d365fo_client-0.3.3.dist-info/RECORD
