Metadata-Version: 2.4
Name: d365fo-client
Version: 0.3.3
Summary: Microsoft Dynamics 365 Finance & Operations client
Author-email: Muhammad Afzaal <mo@thedataguy.pro>
License-Expression: MIT
Project-URL: Homepage, https://github.com/mafzaal/d365fo-client
Project-URL: Repository, https://github.com/mafzaal/d365fo-client
Project-URL: Documentation, https://github.com/mafzaal/d365fo-client
Project-URL: Issues, https://github.com/mafzaal/d365fo-client/issues
Project-URL: Changelog, https://github.com/mafzaal/d365fo-client/blob/main/CHANGELOG.md
Keywords: dynamics365,d365,finance,operations,erp,microsoft
Classifier: Development Status :: 3 - Alpha
Classifier: Intended Audience :: Developers
Classifier: Programming Language :: Python :: 3
Classifier: Programming Language :: Python :: 3.13
Classifier: Topic :: Office/Business :: Financial
Classifier: Topic :: Software Development :: Libraries :: Python Modules
Requires-Python: >=3.13
License-File: LICENSE
Requires-Dist: aiohttp>=3.10.0
Requires-Dist: aiofiles>=24.1.0
Requires-Dist: azure-identity>=1.19.0
Requires-Dist: azure-keyvault-secrets>=4.8.0
Requires-Dist: requests>=2.32.0
Requires-Dist: aiosqlite>=0.19.0
Requires-Dist: cachetools>=6.1.0
Requires-Dist: diskcache>=5.6.3
Requires-Dist: tabulate>=0.9.0
Requires-Dist: pyyaml>=6.0
Requires-Dist: mcp>=1.13.0
Requires-Dist: uvicorn>=0.32.0
Requires-Dist: pydantic-settings>=2.6.0
Requires-Dist: authlib>=1.6.4
Requires-Dist: httpx>=0.28.1
Requires-Dist: rich>=14.1.0
Provides-Extra: dev
Requires-Dist: pytest>=8.0.0; extra == "dev"
Requires-Dist: pytest-asyncio>=0.23.0; extra == "dev"
Requires-Dist: pytest-cov>=4.0.0; extra == "dev"
Requires-Dist: black>=23.0.0; extra == "dev"
Requires-Dist: ruff>=0.1.0; extra == "dev"
Provides-Extra: all
Requires-Dist: d365fo-client[dev]; extra == "all"
Dynamic: license-file
